yhnews/__init__.py
yhnews/yhnews.py
yhnews-0.0.1.dist-info/LICENSE
yhnews-0.0.1.dist-info/METADATA
yhnews-0.0.1.dist-info/WHEEL
yhnews-0.0.1.dist-info/top_level.txt
yhnews-0.0.1.dist-info/RECORD
