Metadata-Version: 2.1
Name: yhnews
Version: 0.0.1
Summary: news for event clustering.
Home-page: https://github.com/geodge831012
Author: geodgechen
Author-email: geodge831012@163.com
Maintainer: geodgechen
Maintainer-email: geodge831012@163.com
License: Copyright (C) 2019 The Python Packaging Authority
